app01/__init__.py
app01/cli.py
app01/config/__init__.py
app01/config/oss_config.py
app01/config/oss_helper.py
app01/matt/__init__.py
app01/matt/math_add.py
app01-0.1.6.dist-info/AUTHORS.rst
app01-0.1.6.dist-info/LICENSE
app01-0.1.6.dist-info/METADATA
app01-0.1.6.dist-info/WHEEL
app01-0.1.6.dist-info/entry_points.txt
app01-0.1.6.dist-info/top_level.txt
app01-0.1.6.dist-info/RECORD
