Metadata-Version: 2.1
Name: app01
Version: 0.1.6
Summary: my first app01
Home-page: https://github.com/near2sea/app01
Author: lihaijian
Author-email: sanan.li@qq.com
License: MIT license
Keywords: app01
Classifier: Development Status :: 2 - Pre-Alpha
Classifier: Intended Audience :: Developers
Classifier: License :: OSI Approved :: MIT License
Classifier: Natural Language :: English
Classifier: Programming Language :: Python :: 3
Classifier: Programming Language :: Python :: 3.6
Classifier: Programming Language :: Python :: 3.7
Classifier: Programming Language :: Python :: 3.8
Requires-Python: >=3.6
License-File: LICENSE
License-File: AUTHORS.rst
Requires-Dist: pip
Requires-Dist: setuptools
Provides-Extra: dev
Requires-Dist: pytest ; extra == 'dev'
Requires-Dist: responses ; extra == 'dev'
Requires-Dist: pytest-mock ; extra == 'dev'
Requires-Dist: werkzeug (<2.1.0) ; extra == 'dev'
Requires-Dist: flake8 ; extra == 'dev'
Requires-Dist: flake8-comprehensions ; extra == 'dev'
Requires-Dist: flake8-deprecated ; extra == 'dev'
Requires-Dist: flake8-mutable ; extra == 'dev'
Requires-Dist: flake8-tuple ; extra == 'dev'
Requires-Dist: twine ; extra == 'dev'
Requires-Dist: wheel ; extra == 'dev'
Requires-Dist: oss2 ; extra == 'dev'
Provides-Extra: test
Requires-Dist: pytest ; extra == 'test'
Requires-Dist: responses ; extra == 'test'
Requires-Dist: pytest-mock ; extra == 'test'
Requires-Dist: werkzeug (<2.1.0) ; extra == 'test'
